MANIFEST.in
README.md
setup.py
shufflecast/__init__.py
shufflecast/shufflecast.py
shufflecast.egg-info/PKG-INFO
shufflecast.egg-info/SOURCES.txt
shufflecast.egg-info/dependency_links.txt
shufflecast.egg-info/entry_points.txt
shufflecast.egg-info/not-zip-safe
shufflecast.egg-info/requires.txt
shufflecast.egg-info/top_level.txt