Metadata-Version: 1.1
Name: shufflecast
Version: 0.1.2
Summary: A TV channel with all your favorite shows.
Home-page: https://github.com/skorokithakis/shufflecast
Author: Stavros Korokithakis
Author-email: hi@stavros.io
License: BSD
Keywords: shufflecast
Platform: UNKNOWN
Classifier: Development Status :: 2 - Pre-Alpha
Classifier: Intended Audience :: Developers
Classifier: License :: OSI Approved :: BSD License
Classifier: Natural Language :: English
Classifier: Programming Language :: Python :: 2
Classifier: Programming Language :: Python :: 2.7
Classifier: Programming Language :: Python :: 3
Classifier: Programming Language :: Python :: 3.3
Classifier: Programming Language :: Python :: 3.4
